arxiv2text/__init__.py
arxiv2text/constant.py
arxiv2text/search.py
arxiv2text/utils.py
arxiv2text/convert/__init__.py
arxiv2text/convert/to_html.py
arxiv2text/convert/to_markdown.py
arxiv2text/convert/to_text.py
arxiv2text-0.1.14.dist-info/LICENSE
arxiv2text-0.1.14.dist-info/METADATA
arxiv2text-0.1.14.dist-info/WHEEL
arxiv2text-0.1.14.dist-info/entry_points.txt
arxiv2text-0.1.14.dist-info/top_level.txt
arxiv2text-0.1.14.dist-info/RECORD
