Metadata-Version: 2.1
Name: arxiv2text
Version: 0.1.14
Summary: Converting PDF files to text, mainly with a focus on arXiv papers.
Home-page: https://github.com/dsdanielpark/arxiv2text
Author: daniel park
Author-email: parkminwoo1991@gmail.com
Keywords: Python,Paper,Data Mining,Translation
Classifier: Development Status :: 3 - Alpha
Classifier: Intended Audience :: Science/Research
Classifier: Natural Language :: English
Classifier: Programming Language :: Python
Classifier: Programming Language :: Python :: 3.6
Classifier: Programming Language :: Python :: 3.7
Classifier: Programming Language :: Python :: 3.8
Classifier: Topic :: Scientific/Engineering :: Artificial Intelligence
Requires-Python: >=3.6
License-File: LICENSE
Requires-Dist: beautifulsoup4
Requires-Dist: pdfminer-six
Requires-Dist: scikit-learn
Requires-Dist: PyPDF2
